bielik/__init__.py
bielik/__main__.py
bielik/cli.py
bielik/client.py
bielik/config.py
bielik/content_processor.py
bielik/folder_scanner.py
bielik/hf_models.py
bielik/image_analyzer.py
bielik/optimized_loading.py
bielik/progress_logger.py
bielik/project_manager.py
bielik/server.py
bielik/validators.py
bielik-0.2.10.dist-info/licenses/LICENSE
bielik-0.2.10.dist-info/METADATA
bielik-0.2.10.dist-info/WHEEL
bielik-0.2.10.dist-info/entry_points.txt
bielik-0.2.10.dist-info/top_level.txt
bielik-0.2.10.dist-info/RECORD
