Metadata-Version: 2.4
Name: bielik
Version: 0.2.10
Summary: Bielik — Local-first AI assistant with HuggingFace and SpeakLeash models
Author: Tom Sapletta
License-Expression: Apache-2.0
Keywords: llm,chat,huggingface,bielik,polish,ai,assistant
Classifier: Development Status :: 4 - Beta
Classifier: Intended Audience :: Developers
Classifier: Intended Audience :: End Users/Desktop
Classifier: Programming Language :: Python :: 3
Classifier: Programming Language :: Python :: 3.9
Classifier: Programming Language :: Python :: 3.10
Classifier: Programming Language :: Python :: 3.11
Classifier: Topic :: Software Development :: Libraries
Classifier: Topic :: Communications :: Chat
Classifier: Topic :: Scientific/Engineering :: Artificial Intelligence
Classifier: Operating System :: POSIX :: Linux
Classifier: Operating System :: MacOS :: MacOS X
Classifier: Operating System :: Microsoft :: Windows
Classifier: Natural Language :: Polish
Classifier: Natural Language :: English
Requires-Python: >=3.9
License-File: LICENSE
Requires-Dist: typer<1.0.0,>=0.9.0
Requires-Dist: rich<14.0.0,>=13.0.0
Requires-Dist: python-dotenv<2.0.0,>=1.0.0
Requires-Dist: pypdf<4.0.0,>=3.0.0
Requires-Dist: python-docx<1.0.0,>=0.8.11
Requires-Dist: beautifulsoup4<5.0.0,>=4.8.0
Requires-Dist: html2text<2025.0.0,>=2020.1.16
Requires-Dist: huggingface-hub<1.0.0,>=0.16.0
Requires-Dist: tokenizers<1.0.0,>=0.13.0
Requires-Dist: sentencepiece<1.0.0,>=0.1.99
Requires-Dist: protobuf<5.0.0,>=4.21.0
Provides-Extra: local
Requires-Dist: llama-cpp-python<1.0.0,>=0.2.0; extra == "local"
Requires-Dist: sentence-transformers<3.0.0,>=2.2.0; extra == "local"
Provides-Extra: gpu
Requires-Dist: bielik[local]; extra == "gpu"
Requires-Dist: torch<3.0.0,>=2.0.0; extra == "gpu"
Requires-Dist: transformers<5.0.0,>=4.30.0; extra == "gpu"
Requires-Dist: accelerate<1.0.0,>=0.20.0; extra == "gpu"
Requires-Dist: bitsandbytes<1.0.0,>=0.40.0; extra == "gpu"
Provides-Extra: ai
Requires-Dist: bielik[gpu]; extra == "ai"
Requires-Dist: transformers[torch]<5.0.0,>=4.30.0; extra == "ai"
Requires-Dist: datasets<3.0.0,>=2.12.0; extra == "ai"
Requires-Dist: evaluate<1.0.0,>=0.4.0; extra == "ai"
Provides-Extra: dev
Requires-Dist: bielik[ai]; extra == "dev"
Requires-Dist: pytest<8.0.0,>=7.0.0; extra == "dev"
Requires-Dist: pytest-cov<5.0.0,>=4.0.0; extra == "dev"
Requires-Dist: flake8<7.0.0,>=6.0.0; extra == "dev"
Requires-Dist: black<24.0.0,>=23.0.0; extra == "dev"
Requires-Dist: isort<6.0.0,>=5.12.0; extra == "dev"
Requires-Dist: mypy<2.0.0,>=1.0.0; extra == "dev"
Requires-Dist: build<1.0.0,>=0.10.0; extra == "dev"
Requires-Dist: twine<5.0.0,>=4.0.0; extra == "dev"
Requires-Dist: pre-commit<4.0.0,>=3.0.0; extra == "dev"
Provides-Extra: docs
Requires-Dist: mkdocs<2.0.0,>=1.4.0; extra == "docs"
Requires-Dist: mkdocs-material<10.0.0,>=9.0.0; extra == "docs"
Requires-Dist: mkdocstrings[python]<1.0.0,>=0.20.0; extra == "docs"
Provides-Extra: test
Requires-Dist: pytest<8.0.0,>=7.0.0; extra == "test"
Requires-Dist: pytest-cov<5.0.0,>=4.0.0; extra == "test"
Requires-Dist: pytest-mock<4.0.0,>=3.10.0; extra == "test"
Requires-Dist: pytest-asyncio<1.0.0,>=0.20.0; extra == "test"
Provides-Extra: completion
Requires-Dist: click-completion<1.0.0,>=0.5.0; extra == "completion"
Requires-Dist: shellingham<2.0.0,>=1.5.0; extra == "completion"
Provides-Extra: web
Requires-Dist: fastapi<1.0.0,>=0.95.0; extra == "web"
Requires-Dist: uvicorn[standard]<1.0.0,>=0.21.0; extra == "web"
Requires-Dist: jinja2<4.0.0,>=3.0.0; extra == "web"
Requires-Dist: python-multipart<1.0.0,>=0.0.6; extra == "web"
Provides-Extra: all
Requires-Dist: bielik[ai,completion,dev,docs,test,web]; extra == "all"
Dynamic: license-file
